apify_haystack/__init__.py
apify_haystack/apify_dataset.py
apify_haystack/constants.py
apify_haystack/examples/apify_actor_call.py
apify_haystack/examples/apify_dataset_load.py
apify_haystack/examples/crawl_and_process_data.py
apify_haystack/examples/instagram_comments_analysis.py
apify_haystack/examples/rag_with_crawled_website.py
apify_haystack-0.1.7.dist-info/LICENSE
apify_haystack-0.1.7.dist-info/METADATA
apify_haystack-0.1.7.dist-info/WHEEL
apify_haystack-0.1.7.dist-info/RECORD
