Metadata-Version: 2.1
Name: apify_haystack
Version: 0.1.7
Summary: Apify-haystack integration
Home-page: https://apify.com
License: Apache-2.0
Keywords: apify,crawler,haystack,rag,scraper,scraping
Author: Apify Technologies s.r.o.
Author-email: support@apify.com
Requires-Python: >=3.9,<4.0
Classifier: Development Status :: 5 - Production/Stable
Classifier: Intended Audience :: Developers
Classifier: License :: OSI Approved :: Apache Software License
Classifier: Operating System :: OS Independent
Classifier: Programming Language :: Python :: 3
Classifier: Programming Language :: Python :: 3.9
Classifier: Programming Language :: Python :: 3.10
Classifier: Programming Language :: Python :: 3.11
Classifier: Programming Language :: Python :: 3.12
Classifier: Programming Language :: Python :: 3.13
Classifier: Topic :: Software Development :: Libraries
Requires-Dist: apify-client (>=1.7.1,<2.0.0)
Requires-Dist: haystack-ai (>=2.3.1,<3.0.0)
Requires-Dist: python-dotenv (>=1.0.1,<2.0.0)
Project-URL: Changelog, https://github.com/apify/apify-haystack/blob/master/CHANGELOG.md
Project-URL: Documentation, https://github.com/apify/apify-haystack
Project-URL: Issue Tracker, https://github.com/apify/apify-haystack/issues
Project-URL: Repository, https://github.com/apify/apify-haystack
